{
	"id": "12345678-1234-1234-1234-123456789xyz",
	"name": "SIGO API Environment",
	"values": [
		{
			"key": "base_url",
			"value": "http://localhost:4001",
			"type": "default",
			"enabled": true
		},
		{
			"key": "x_email",
			"value": "tu_email@ejemplo.com",
			"type": "secret",
			"enabled": true
		},
		{
			"key": "x_api_key",
			"value": "tu_api_key_de_sigo",
			"type": "secret",
			"enabled": true
		},
		{
			"key": "webhook_secret",
			"value": "tu_webhook_secret_key",
			"type": "secret",
			"enabled": true
		},
		{
			"key": "x_hub_signature",
			"value": "tu_webhook_secret_key",
			"type": "default",
			"enabled": true
		},
		{
			"key": "x_hub_signature_generated",
			"value": "",
			"type": "default",
			"enabled": true
		}
	],
	"_postman_variable_scope": "environment",
	"_postman_exported_at": "2025-01-01T00:00:00.000Z",
	"_postman_exported_using": "Postman/10.20.0"
}